custompublicdatareader/PublicDataPortal/__init__.py
custompublicdatareader/PublicDataPortal/kamco.py
custompublicdatareader/PublicDataPortal/molit.py
custompublicdatareader/PublicDataPortal/nts.py
custompublicdatareader/PublicDataPortal/reb.py
custompublicdatareader/PublicDataPortal/semas.py
custompublicdatareader/Seoul/__init__.py
custompublicdatareader/Seoul/transportation.py
custompublicdatareader/__init__.py
custompublicdatareader/config/__init__.py
custompublicdatareader/config/info.py
custompublicdatareader/data.py
custompublicdatareader/ecos/__init__.py
custompublicdatareader/ecos/ecos.py
custompublicdatareader/fred/__init__.py
custompublicdatareader/fred/fred.py
custompublicdatareader/kbland/__init__.py
custompublicdatareader/kbland/kbland.py
custompublicdatareader/kosis/__init__.py
custompublicdatareader/kosis/kosis.py
custompublicdatareader/raw/KIKcd_B.20230501(말소코드포함).xlsx
custompublicdatareader/raw/KIKcd_H.20230501(말소코드포함).xlsx
custompublicdatareader/raw/KIKmix.20230501(말소코드포함).xlsx
custompublicdatareader/raw/code_bdong.json
custompublicdatareader/raw/code_hdong.json
custompublicdatareader/raw/code_hdong_bdong.json
custompublicdatareader/raw/code_vworld.json
custompublicdatareader/utils/__init__.py
custompublicdatareader/utils/code.py
custompublicdatareader/vworld/__init__.py
custompublicdatareader/vworld/data.py
custompublicdatareader-0.1.3.dist-info/LICENSE
custompublicdatareader-0.1.3.dist-info/METADATA
custompublicdatareader-0.1.3.dist-info/WHEEL
custompublicdatareader-0.1.3.dist-info/RECORD
