Metadata-Version: 2.1
Name: custompublicdatareader
Version: 0.1.3
Summary: 
Author: Your Name
Author-email: you@example.com
Requires-Python: >=3.9.19,<4.0.0
Classifier: Programming Language :: Python :: 3
Classifier: Programming Language :: Python :: 3.10
Classifier: Programming Language :: Python :: 3.11
Classifier: Programming Language :: Python :: 3.12
Requires-Dist: beautifulsoup4 (>=4.12.3,<5.0.0)
Requires-Dist: lxml (>=5.2.2,<6.0.0)
Requires-Dist: numpy (>=2.0.1,<3.0.0)
Requires-Dist: pandas (>=2.2.2,<3.0.0)
Requires-Dist: requests (>=2.32.3,<3.0.0)
Requires-Dist: xmltodict (>=0.13.0,<0.14.0)
